bar_protonmail/__init__.py
bar_protonmail/app.py
bar_protonmail/icon.svg
bar_protonmail/printer.py
bar_protonmail/protonmail.py
bar_protonmail-1.2.0.dist-info/LICENSE
bar_protonmail-1.2.0.dist-info/METADATA
bar_protonmail-1.2.0.dist-info/WHEEL
bar_protonmail-1.2.0.dist-info/entry_points.txt
bar_protonmail-1.2.0.dist-info/RECORD
