Metadata-Version: 2.1
Name: bar-protonmail
Version: 1.2.0
Summary: Get notifications and unread messages count from ProtonMail (Waybar/Polybar module)
Home-page: https://github.com/crabvk/bar-protonmail
License: MIT
Keywords: waybar,polybar,protonmail
Author: Vyacheslav Konovalov
Author-email: crabvk@protonmail.com
Requires-Python: >=3.10,<4.0
Classifier: Environment :: Console
Classifier: License :: OSI Approved :: MIT License
Classifier: Operating System :: OS Independent
Classifier: Programming Language :: Python :: 3
Classifier: Programming Language :: Python :: 3.10
Classifier: Programming Language :: Python :: 3.11
Classifier: Programming Language :: Python :: 3.12
Requires-Dist: dasbus (>=1.7,<2.0)
Requires-Dist: dnspython (>=2.2.1,<3.0.0)
Requires-Dist: proton-client (>=0.7.1,<0.8.0)
Requires-Dist: pygobject (>=3.46.0,<4.0.0)
Requires-Dist: pysocks (>=1.7.1,<2.0.0)
